schemon/__init__.py
schemon/common.py
schemon/config.py
schemon/dao.py
schemon/env.py
schemon/main.py
schemon/migrate.py
schemon/model.py
schemon/publish.py
schemon/sqlparser.py
schemon/validate.py
schemon/validator.py
schemon/antlr/__init__.py
schemon/antlr/spark/SqlBaseLexer.py
schemon/antlr/spark/SqlBaseParser.py
schemon/antlr/spark/SqlBaseParserListener.py
schemon/antlr/spark/__init__.py
schemon/domain/__init__.py
schemon/domain/base.py
schemon/domain/contract/__init__.py
schemon/domain/contract/config.py
schemon/domain/contract/contract.py
schemon/domain/contract/entity.py
schemon/domain/contract/expectation.py
schemon/domain/contract/field.py
schemon/domain/contract/owner.py
schemon/domain/contract/task.py
schemon/migration/__init__.py
schemon/migration/database.py
schemon/migration/databricks_service.py
schemon/migration/init.py
schemon/migration/revision.py
schemon/migration/template/README
schemon/migration/template/__init__.py
schemon/migration/template/alembic.ini.mako
schemon/migration/template/env.py
schemon/migration/template/script.py.mako
schemon/notebook/__init__.py
schemon/notebook/base/__init__.py
schemon/notebook/base/config.py
schemon/notebook/base/executor_manager.py
schemon/notebook/base/notebook.py
schemon/notebook/base/platform_manager.py
schemon/notebook/base/section.py
schemon/notebook/base/store.py
schemon/notebook/base/type_mapping.py
schemon/notebook/engine/__init__.py
schemon/notebook/engine/spark/__init__.py
schemon/notebook/engine/spark/spark_config.py
schemon/notebook/engine/spark/spark_listener.py
schemon/notebook/engine/spark/spark_notebook.py
schemon/notebook/engine/spark/spark_notebook_config.py
schemon/notebook/engine/spark/spark_section.py
schemon/notebook/engine/spark/spark_section_config.py
schemon/notebook/engine/spark/spark_type_mapping.py
schemon/notebook/executor_manager/__init__.py
schemon/notebook/executor_manager/process_pool_executor_manager.py
schemon/notebook/executor_manager/spark_native_executor_manager.py
schemon-0.0.35.dist-info/LICENSE
schemon-0.0.35.dist-info/METADATA
schemon-0.0.35.dist-info/NOTICE
schemon-0.0.35.dist-info/WHEEL
schemon-0.0.35.dist-info/entry_points.txt
schemon-0.0.35.dist-info/top_level.txt
schemon-0.0.35.dist-info/RECORD
