Metadata-Version: 2.1
Name: schemon
Version: 0.0.35
Summary: UNKNOWN
Home-page: UNKNOWN
License: SCHEMON INC. PROPRIETARY LICENSE
Platform: UNKNOWN
Requires-Python: >=3.9
License-File: LICENSE
License-File: NOTICE
Requires-Dist: future==1.0.0
Requires-Dist: greenlet==3.0.3
Requires-Dist: pure-sasl==0.6.2
Requires-Dist: PyHive==0.7.0
Requires-Dist: python-dateutil==2.9.0.post0
Requires-Dist: PyYAML==6.0.1
Requires-Dist: six==1.16.0
Requires-Dist: SQLAlchemy==2.0.31
Requires-Dist: thrift==0.20.0
Requires-Dist: thrift-sasl==0.4.3
Requires-Dist: typing-extensions==4.12.2
Requires-Dist: python-dotenv==1.0.0
Requires-Dist: databricks-sql-connector[sqlalchemy]==3.2.0
Requires-Dist: prettytable==3.10.0
Requires-Dist: antlr4-python3-runtime==4.13.1
Requires-Dist: requests==2.32.3
Requires-Dist: charset-normalizer==3.1.0
Requires-Dist: alembic==1.13.2
Requires-Dist: nicegui==1.4.36
Requires-Dist: pyodbc==5.1.0
Requires-Dist: pyspark==3.5.0
Requires-Dist: delta-spark==3.2.0
Requires-Dist: schemon-python-logger
Requires-Dist: schemon-python-client
